{"updated": "2026-04-09T01:03:47.411614Z", "count": 294, "videos": [{"id": "h3DCdWyb0cc", "title": "The Most Insane Megaproject You Never Heard About", "channel": "Kurzgesagt \u2013 In a Nutshell", "thumb": "https://img.youtube.com/vi/h3DCdWyb0cc/mqdefault.jpg"}, {"id": "MX_r0KsMpho", "title": "Spaceships Powered by Nukes", "channel": "Kurzgesagt \u2013 In a Nutshell", "thumb": "https://img.youtube.com/vi/MX_r0KsMpho/mqdefault.jpg"}, {"id": "NXhKuMQRAZ4", "title": "Queen Ant Clones Another Species", "channel": "Kurzgesagt \u2013 In a Nutshell", "thumb": "https://img.youtube.com/vi/NXhKuMQRAZ4/mqdefault.jpg"}, {"id": "5Xd38M9zTjM", "title": "Let\u2019s Tie All Planets Together", "channel": "Kurzgesagt \u2013 In a Nutshell", "thumb": "https://img.youtube.com/vi/5Xd38M9zTjM/mqdefault.jpg"}, {"id": "YHlqwkdVda8", "title": "Who Owns Your Drinking Water?", "channel": "Kurzgesagt \u2013 In a Nutshell", "thumb": "https://img.youtube.com/vi/YHlqwkdVda8/mqdefault.jpg"}, {"id": "5EPPBDdhe6o", "title": "The Worm with 4 Nobel Prizes", "channel": "Kurzgesagt \u2013 In a Nutshell", "thumb": "https://img.youtube.com/vi/5EPPBDdhe6o/mqdefault.jpg"}, {"id": "zg40FHOAqC0", "title": "Jupiter Made Earth Possible", "channel": "Kurzgesagt \u2013 In a Nutshell", "thumb": "https://img.youtube.com/vi/zg40FHOAqC0/mqdefault.jpg"}, {"id": "m2BE9GZJJbs", "title": "How do snakes swallow animals so much bigger than they are? - Niko Zlotnik", "channel": "TED-Ed", "thumb": "https://img.youtube.com/vi/m2BE9GZJJbs/mqdefault.jpg"}, {"id": "QWCHnR53oIw", "title": "What happens if you eat a silica gel packet? - Vivian Jiang", "channel": "TED-Ed", "thumb": "https://img.youtube.com/vi/QWCHnR53oIw/mqdefault.jpg"}, {"id": "UDdkgOoeNcQ", "title": "Do artists really write their own songs? | Think Like A Musician", "channel": "TED-Ed", "thumb": "https://img.youtube.com/vi/UDdkgOoeNcQ/mqdefault.jpg"}, {"id": "D98UJl6Ea6o", "title": "One of the world\u2019s oldest beverages - Malcolm Purinton", "channel": "TED-Ed", "thumb": "https://img.youtube.com/vi/D98UJl6Ea6o/mqdefault.jpg"}, {"id": "lQRsqMiBTsI", "title": "3 surprising ways microplastics can enter your body", "channel": "TED-Ed", "thumb": "https://img.youtube.com/vi/lQRsqMiBTsI/mqdefault.jpg"}, {"id": "iCBzEZek5cY", "title": "How long can hair grow? - Maksim Plikus", "channel": "TED-Ed", "thumb": "https://img.youtube.com/vi/iCBzEZek5cY/mqdefault.jpg"}, {"id": "gVXoAbeB8QI", "title": "What happens when you break a bone? - Gurpreet Baht and Natalie Pang", "channel": "TED-Ed", "thumb": "https://img.youtube.com/vi/gVXoAbeB8QI/mqdefault.jpg"}, {"id": "-Tw81EQYV_Y", "title": "How hat fashion has evolved throughout history - Alison L. Goodrum", "channel": "TED-Ed", "thumb": "https://img.youtube.com/vi/-Tw81EQYV_Y/mqdefault.jpg"}, {"id": "wxf_pKCOCBo", "title": "The biggest mistake lottery winners make", "channel": "TED-Ed", "thumb": "https://img.youtube.com/vi/wxf_pKCOCBo/mqdefault.jpg"}, {"id": "JJdoAMiaLZo", "title": "Does hypnosis ever actually work? - Devin Terhune", "channel": "TED-Ed", "thumb": "https://img.youtube.com/vi/JJdoAMiaLZo/mqdefault.jpg"}, {"id": "MBir652KZPE", "title": "How expert songwriters find the right lyrics | Think Like A Musician", "channel": "TED-Ed", "thumb": "https://img.youtube.com/vi/MBir652KZPE/mqdefault.jpg"}, {"id": "EtiC0DVewa4", "title": "The biggest myths about Neanderthals - Bruce Hardy", "channel": "TED-Ed", "thumb": "https://img.youtube.com/vi/EtiC0DVewa4/mqdefault.jpg"}, {"id": "GOmQwinZKtE", "title": "Testing Every Seat on a Log Ride", "channel": "Mark Rober", "thumb": "https://img.youtube.com/vi/GOmQwinZKtE/mqdefault.jpg"}, {"id": "wJMrk69WOdw", "title": "The SECRET to Fighting Laundry Stains #TidePartner", "channel": "Mark Rober", "thumb": "https://img.youtube.com/vi/wJMrk69WOdw/mqdefault.jpg"}, {"id": "VZ0oIzvzkGI", "title": "Secret To Defusing A Soda Grenade", "channel": "Mark Rober", "thumb": "https://img.youtube.com/vi/VZ0oIzvzkGI/mqdefault.jpg"}, {"id": "Xg1ro-zG7AM", "title": "Engineers vs Junkyard RC Car Death Match", "channel": "Mark Rober", "thumb": "https://img.youtube.com/vi/Xg1ro-zG7AM/mqdefault.jpg"}, {"id": "YPOfYntrrcU", "title": "Your fingers are actually a clock", "channel": "Mark Rober", "thumb": "https://img.youtube.com/vi/YPOfYntrrcU/mqdefault.jpg"}, {"id": "9BsQpGhwVAY", "title": "pride comes before flop", "channel": "Mark Rober", "thumb": "https://img.youtube.com/vi/9BsQpGhwVAY/mqdefault.jpg"}, {"id": "kgSHJhX6ly0", "title": "Can You Ship A Potato Through The Mail?", "channel": "Mark Rober", "thumb": "https://img.youtube.com/vi/kgSHJhX6ly0/mqdefault.jpg"}, {"id": "c4dH8MpXYH4", "title": "Disney\u2019s Secret for Making Ghosts REAL", "channel": "Mark Rober", "thumb": "https://img.youtube.com/vi/c4dH8MpXYH4/mqdefault.jpg"}, {"id": "lSDoCbQsKxY", "title": "Why The Weatherman Is Always Wrong!", "channel": "Mark Rober", "thumb": "https://img.youtube.com/vi/lSDoCbQsKxY/mqdefault.jpg"}, {"id": "qsJgJjOG5tY", "title": "How Close To Beat My Goalie Robot?", "channel": "Mark Rober", "thumb": "https://img.youtube.com/vi/qsJgJjOG5tY/mqdefault.jpg"}, {"id": "lNOjw3KRsqg", "title": "How Superglue Actually Works", "channel": "Mark Rober", "thumb": "https://img.youtube.com/vi/lNOjw3KRsqg/mqdefault.jpg"}, {"id": "oZOCmEDROHY", "title": "Help Me Pass Ronaldo in Subscribers!", "channel": "Mark Rober", "thumb": "https://img.youtube.com/vi/oZOCmEDROHY/mqdefault.jpg"}, {"id": "AGUO3YQ_Y38", "title": "Ronaldo vs My Goalie Robot", "channel": "Mark Rober", "thumb": "https://img.youtube.com/vi/AGUO3YQ_Y38/mqdefault.jpg"}, {"id": "jjpjjcMeujM", "title": "Ronaldo vs My Unbeatable Goalie Robot", "channel": "Mark Rober", "thumb": "https://img.youtube.com/vi/jjpjjcMeujM/mqdefault.jpg"}, {"id": "-0JKHuzJ67A", "title": "Everything About Disc Golf Aerodynamics - Smarter Every Day 313", "channel": "SmarterEveryDay", "thumb": "https://img.youtube.com/vi/-0JKHuzJ67A/mqdefault.jpg"}, {"id": "XwBZx1cXEdM", "title": "Why Do Spinning Things Do This? - Smarter Every Day 312", "channel": "SmarterEveryDay", "thumb": "https://img.youtube.com/vi/XwBZx1cXEdM/mqdefault.jpg"}, {"id": "dt_CG_xRnrY", "title": "Pompeii Changed How I Think About The Roman Empire - Smarter Every Day 310", "channel": "SmarterEveryDay", "thumb": "https://img.youtube.com/vi/dt_CG_xRnrY/mqdefault.jpg"}, {"id": "3ZTGwcHQfLY", "title": "I Tried To Make Something In America (The Smarter Scrubber Experiment) - Smarter Every Day 308", "channel": "SmarterEveryDay", "thumb": "https://img.youtube.com/vi/3ZTGwcHQfLY/mqdefault.jpg"}, {"id": "8nilP--GFLY", "title": "The Unsolved Mystery of Impact Flashes - Smarter Every Day 307", "channel": "SmarterEveryDay", "thumb": "https://img.youtube.com/vi/8nilP--GFLY/mqdefault.jpg"}, {"id": "lylCYkgC63Q", "title": "The Backwards Brain Tractor - Smarter Every Day 305", "channel": "SmarterEveryDay", "thumb": "https://img.youtube.com/vi/lylCYkgC63Q/mqdefault.jpg"}, {"id": "JJofuF2zcTE", "title": "Live Interview from the ISS Cupola - Smarter Every Day 303", "channel": "SmarterEveryDay", "thumb": "https://img.youtube.com/vi/JJofuF2zcTE/mqdefault.jpg"}, {"id": "sEK6wZWMbCY", "title": "Climbing Kilimanjaro - Smarter Every Day 302", "channel": "SmarterEveryDay", "thumb": "https://img.youtube.com/vi/sEK6wZWMbCY/mqdefault.jpg"}, {"id": "frbLIoqDIO8", "title": "How Disc Golf Discs Are Made (MVP Manufacturing Tour) - Smarter Every Day 301", "channel": "SmarterEveryDay", "thumb": "https://img.youtube.com/vi/frbLIoqDIO8/mqdefault.jpg"}, {"id": "VPSm9gJkPxU", "title": "Nature's Incredible ROTATING MOTOR (It\u2019s Electric!) - Smarter Every Day 300", "channel": "SmarterEveryDay", "thumb": "https://img.youtube.com/vi/VPSm9gJkPxU/mqdefault.jpg"}, {"id": "TWc48iVC8u8", "title": "How Do Cicadas Make Noise? (In Slow Motion)  - Smarter Every Day 299", "channel": "SmarterEveryDay", "thumb": "https://img.youtube.com/vi/TWc48iVC8u8/mqdefault.jpg"}, {"id": "BU5HwNyE4mk", "title": "The Bizarre Behaviour Of Rotating Bodies", "channel": "Veritasium", "thumb": "https://img.youtube.com/vi/BU5HwNyE4mk/mqdefault.jpg"}, {"id": "YSJY3DvnybE", "title": "The Secret Spy Tech Inside Every Credit Card", "channel": "Veritasium", "thumb": "https://img.youtube.com/vi/YSJY3DvnybE/mqdefault.jpg"}, {"id": "zP5uhMpH4mE", "title": "How Pressure Can Come From *Nothing*", "channel": "Veritasium", "thumb": "https://img.youtube.com/vi/zP5uhMpH4mE/mqdefault.jpg"}, {"id": "9szhjhO9epA", "title": "Why are these 3 letters on almost all of my zippers?", "channel": "Veritasium", "thumb": "https://img.youtube.com/vi/9szhjhO9epA/mqdefault.jpg"}, {"id": "R8oiho_gKSo", "title": "The Shadow Illusion", "channel": "Veritasium", "thumb": "https://img.youtube.com/vi/R8oiho_gKSo/mqdefault.jpg"}, {"id": "Ol18JoeXlVI", "title": "This Paradox Splits Smart People 50/50", "channel": "Veritasium", "thumb": "https://img.youtube.com/vi/Ol18JoeXlVI/mqdefault.jpg"}, {"id": "DJ_5_JS9_Rs", "title": "You Can't Feel Wet", "channel": "Veritasium", "thumb": "https://img.youtube.com/vi/DJ_5_JS9_Rs/mqdefault.jpg"}, {"id": "qtPPfM7Tz1o", "title": "The Crazy Physics of Jet Engines", "channel": "Veritasium", "thumb": "https://img.youtube.com/vi/qtPPfM7Tz1o/mqdefault.jpg"}, {"id": "Bl0WZvAeDik", "title": "Rubber used to be useless\u2026", "channel": "Veritasium", "thumb": "https://img.youtube.com/vi/Bl0WZvAeDik/mqdefault.jpg"}, {"id": "Bt3boxwRF84", "title": "World\u2019s Largest Spiderweb", "channel": "Veritasium", "thumb": "https://img.youtube.com/vi/Bt3boxwRF84/mqdefault.jpg"}, {"id": "6HVYHNTDOFs", "title": "This Common Substance Was Once Worth Millions", "channel": "Veritasium", "thumb": "https://img.youtube.com/vi/6HVYHNTDOFs/mqdefault.jpg"}, {"id": "XKSjCOKDtpk", "title": "The Tiny Donut That Proved We Still Don't Understand Magnetism", "channel": "Veritasium", "thumb": "https://img.youtube.com/vi/XKSjCOKDtpk/mqdefault.jpg"}, {"id": "WfAmK8u0Mx8", "title": "The IKEA Experience", "channel": "TheOdd1sOut", "thumb": "https://img.youtube.com/vi/WfAmK8u0Mx8/mqdefault.jpg"}, {"id": "Z6Asp8knZ9c", "title": "Sharkmie", "channel": "TheOdd1sOut", "thumb": "https://img.youtube.com/vi/Z6Asp8knZ9c/mqdefault.jpg"}, {"id": "DW6gOS_FGLI", "title": "The Chicago Fishpocalypse", "channel": "TheOdd1sOut", "thumb": "https://img.youtube.com/vi/DW6gOS_FGLI/mqdefault.jpg"}, {"id": "OZHyl2_xtS4", "title": "What's His Name?", "channel": "TheOdd1sOut", "thumb": "https://img.youtube.com/vi/OZHyl2_xtS4/mqdefault.jpg"}, {"id": "uQkBFh7OdGE", "title": "Xerneas Crossing", "channel": "TheOdd1sOut", "thumb": "https://img.youtube.com/vi/uQkBFh7OdGE/mqdefault.jpg"}, {"id": "KfraYu2AVUQ", "title": "Training to be a Warrior", "channel": "TheOdd1sOut", "thumb": "https://img.youtube.com/vi/KfraYu2AVUQ/mqdefault.jpg"}, {"id": "9qIampBhMkA", "title": "Warrior Cat Names", "channel": "TheOdd1sOut", "thumb": "https://img.youtube.com/vi/9qIampBhMkA/mqdefault.jpg"}, {"id": "DIuDn3RvRdo", "title": "The Insane Warrior Cats Fandom", "channel": "TheOdd1sOut", "thumb": "https://img.youtube.com/vi/DIuDn3RvRdo/mqdefault.jpg"}, {"id": "CiAUFesW-eM", "title": "I Want a Hippopotamus for Christmas", "channel": "TheOdd1sOut", "thumb": "https://img.youtube.com/vi/CiAUFesW-eM/mqdefault.jpg"}, {"id": "tZjRK1h7ivM", "title": "30 Minutes + 20 Sandwiches = 9 Starving Boys", "channel": "TheOdd1sOut", "thumb": "https://img.youtube.com/vi/tZjRK1h7ivM/mqdefault.jpg"}, {"id": "sqQZmk5Ffj8", "title": "Crying Over Spilled Lemonade", "channel": "TheOdd1sOut", "thumb": "https://img.youtube.com/vi/sqQZmk5Ffj8/mqdefault.jpg"}, {"id": "hVG8WA1J114", "title": "Google Maps 4", "channel": "TheOdd1sOut", "thumb": "https://img.youtube.com/vi/hVG8WA1J114/mqdefault.jpg"}, {"id": "UIx5Go_ugis", "title": "Animating 1-Star Fast Food Reviews", "channel": "TheOdd1sOut", "thumb": "https://img.youtube.com/vi/UIx5Go_ugis/mqdefault.jpg"}, {"id": "AEGV_kWCHOY", "title": "This Brick is Alive", "channel": "TheOdd1sOut", "thumb": "https://img.youtube.com/vi/AEGV_kWCHOY/mqdefault.jpg"}, {"id": "4VinwOQkHGg", "title": "The Yuckiest Animals | SciShow Kids Compilation", "channel": "SciShow Kids", "thumb": "https://img.youtube.com/vi/4VinwOQkHGg/mqdefault.jpg"}, {"id": "WX_E1CAZjaQ", "title": "KABOOM! All About Volcanoes! | SciShow Kids Compilation", "channel": "SciShow Kids", "thumb": "https://img.youtube.com/vi/WX_E1CAZjaQ/mqdefault.jpg"}, {"id": "0jKoOUZ1GBM", "title": "Every Kind of Volcano | SciShow Kids", "channel": "SciShow Kids", "thumb": "https://img.youtube.com/vi/0jKoOUZ1GBM/mqdefault.jpg"}, {"id": "GJuO4MzYrtI", "title": "Thank You Teachers! | SciShow Kids", "channel": "SciShow Kids", "thumb": "https://img.youtube.com/vi/GJuO4MzYrtI/mqdefault.jpg"}, {"id": "8qdYCpSW2eY", "title": "The Biggest Volcano Ever is in Space! | SciShow Kids", "channel": "SciShow Kids", "thumb": "https://img.youtube.com/vi/8qdYCpSW2eY/mqdefault.jpg"}, {"id": "YR4wtGWK7eE", "title": "Hawai\u2019i: Land of Volcanoes | SciShow Kids", "channel": "SciShow Kids", "thumb": "https://img.youtube.com/vi/YR4wtGWK7eE/mqdefault.jpg"}, {"id": "RvRU_4XWPlw", "title": "Solving Problems Around the Fort! | SciShow Kids", "channel": "SciShow Kids", "thumb": "https://img.youtube.com/vi/RvRU_4XWPlw/mqdefault.jpg"}, {"id": "v8cDsAf0nN0", "title": "Squeaks' Adventure Around The World! | SciShow Kids", "channel": "SciShow Kids", "thumb": "https://img.youtube.com/vi/v8cDsAf0nN0/mqdefault.jpg"}, {"id": "kKqd0_cydZM", "title": "Iceland: A Land of Ice AND Fire! | SciShow Kids", "channel": "SciShow Kids", "thumb": "https://img.youtube.com/vi/kKqd0_cydZM/mqdefault.jpg"}, {"id": "HhXnRfyUbeQ", "title": "The Fiordlands of New Zealand! | SciShow Kids", "channel": "SciShow Kids", "thumb": "https://img.youtube.com/vi/HhXnRfyUbeQ/mqdefault.jpg"}, {"id": "0U4lOGo593k", "title": "Yellowstone: The World\u2019s First National Park! | SciShow Kids", "channel": "SciShow Kids", "thumb": "https://img.youtube.com/vi/0U4lOGo593k/mqdefault.jpg"}, {"id": "annJ7XUxMjk", "title": "Going to the Doctor! | SciShow Kids Compilation", "channel": "SciShow Kids", "thumb": "https://img.youtube.com/vi/annJ7XUxMjk/mqdefault.jpg"}, {"id": "XtSq1wcFSEI", "title": "Your Body's Senses | SciShow Kids Compilation", "channel": "SciShow Kids", "thumb": "https://img.youtube.com/vi/XtSq1wcFSEI/mqdefault.jpg"}, {"id": "vKxpbmdPSyk", "title": "Senses You Didn\u2019t Know You Have | SciShow Kids", "channel": "SciShow Kids", "thumb": "https://img.youtube.com/vi/vKxpbmdPSyk/mqdefault.jpg"}, {"id": "6WNHyAXIN8c", "title": "How Ears Let Us Hear the World! | SciShow Kids", "channel": "SciShow Kids", "thumb": "https://img.youtube.com/vi/6WNHyAXIN8c/mqdefault.jpg"}, {"id": "i45dfK7wYvA", "title": "Schr\u00f6dinger\u2019s Cat (from the cat's perspective)", "channel": "minutephysics", "thumb": "https://img.youtube.com/vi/i45dfK7wYvA/mqdefault.jpg"}, {"id": "0fV8kYoGDNM", "title": "When 2 + 2 = 3.999999999\u2026", "channel": "minutephysics", "thumb": "https://img.youtube.com/vi/0fV8kYoGDNM/mqdefault.jpg"}, {"id": "qqWZg4sZNjk", "title": "Breaking the speed of light from your backyard", "channel": "minutephysics", "thumb": "https://img.youtube.com/vi/qqWZg4sZNjk/mqdefault.jpg"}, {"id": "lZGyjR6Y9vw", "title": "Is Quantum Mechanics Stopping Aliens From Contacting Us?", "channel": "minutephysics", "thumb": "https://img.youtube.com/vi/lZGyjR6Y9vw/mqdefault.jpg"}, {"id": "-kwF6M4juiU", "title": "Not a rainbow!", "channel": "minutephysics", "thumb": "https://img.youtube.com/vi/-kwF6M4juiU/mqdefault.jpg"}, {"id": "YaGEjPdJycA", "title": "What\u2019s the source of gravity? (a common physics misconception)", "channel": "minutephysics", "thumb": "https://img.youtube.com/vi/YaGEjPdJycA/mqdefault.jpg"}, {"id": "kzfXBenNxeA", "title": "The REAL Reason Asteroids Aren't Planets", "channel": "minutephysics", "thumb": "https://img.youtube.com/vi/kzfXBenNxeA/mqdefault.jpg"}, {"id": "xgFKxFX3IwY", "title": "An Argument The Moon is a PLANET!", "channel": "minutephysics", "thumb": "https://img.youtube.com/vi/xgFKxFX3IwY/mqdefault.jpg"}, {"id": "_DYZF-piKKU", "title": "The TROJAN Test", "channel": "minutephysics", "thumb": "https://img.youtube.com/vi/_DYZF-piKKU/mqdefault.jpg"}, {"id": "OEQeSrXy-YA", "title": "Why Some Rainbows Turn White", "channel": "minutephysics", "thumb": "https://img.youtube.com/vi/OEQeSrXy-YA/mqdefault.jpg"}, {"id": "yY7ZUIbWTyc", "title": "Common Moon Mistakes", "channel": "minutephysics", "thumb": "https://img.youtube.com/vi/yY7ZUIbWTyc/mqdefault.jpg"}, {"id": "pgqkti7yePk", "title": "Why Do Wind Turbines Have Three Blades?", "channel": "minutephysics", "thumb": "https://img.youtube.com/vi/pgqkti7yePk/mqdefault.jpg"}, {"id": "zzWKh8W8dX8", "title": "Draining The Oceans Is HARD", "channel": "minutephysics", "thumb": "https://img.youtube.com/vi/zzWKh8W8dX8/mqdefault.jpg"}, {"id": "6c7JoCZmqC4", "title": "The Physics of Supercooling", "channel": "minutephysics", "thumb": "https://img.youtube.com/vi/6c7JoCZmqC4/mqdefault.jpg"}, {"id": "1eNVMWKwncc", "title": "Why is grass greener underneath a trampoline?", "channel": "MinuteEarth", "thumb": "https://img.youtube.com/vi/1eNVMWKwncc/mqdefault.jpg"}, {"id": "f91p64gOFF0", "title": "Could This Thing *Really* Fly?", "channel": "MinuteEarth", "thumb": "https://img.youtube.com/vi/f91p64gOFF0/mqdefault.jpg"}, {"id": "iUbB-e823Qo", "title": "Weavers helped us get to the moon!", "channel": "MinuteEarth", "thumb": "https://img.youtube.com/vi/iUbB-e823Qo/mqdefault.jpg"}, {"id": "JMYN9RpL61s", "title": "The danger isn't over when the storm dies down.", "channel": "MinuteEarth", "thumb": "https://img.youtube.com/vi/JMYN9RpL61s/mqdefault.jpg"}, {"id": "RYCVihgO3g8", "title": "The Coyote Paradox", "channel": "MinuteEarth", "thumb": "https://img.youtube.com/vi/RYCVihgO3g8/mqdefault.jpg"}, {"id": "EXzFQauTBnI", "title": "Where do we get snake antivenom?", "channel": "MinuteEarth", "thumb": "https://img.youtube.com/vi/EXzFQauTBnI/mqdefault.jpg"}, {"id": "hItlmfXZBQU", "title": "40 Years Without A New Antibiotic. Why?", "channel": "MinuteEarth", "thumb": "https://img.youtube.com/vi/hItlmfXZBQU/mqdefault.jpg"}, {"id": "w2X1RF_lqOE", "title": "A Microbial Miracle!", "channel": "MinuteEarth", "thumb": "https://img.youtube.com/vi/w2X1RF_lqOE/mqdefault.jpg"}, {"id": "R8wZJed497Q", "title": "What is a species?", "channel": "MinuteEarth", "thumb": "https://img.youtube.com/vi/R8wZJed497Q/mqdefault.jpg"}, {"id": "jxQdW7COjLk", "title": "Why Hives Turn Against Their Queens", "channel": "MinuteEarth", "thumb": "https://img.youtube.com/vi/jxQdW7COjLk/mqdefault.jpg"}, {"id": "P6Hv_MNiJ_o", "title": "The world changed too fast for this beetle", "channel": "MinuteEarth", "thumb": "https://img.youtube.com/vi/P6Hv_MNiJ_o/mqdefault.jpg"}, {"id": "l33JLE2NhKc", "title": "Why Eagles are Overdubbed In Movies", "channel": "MinuteEarth", "thumb": "https://img.youtube.com/vi/l33JLE2NhKc/mqdefault.jpg"}, {"id": "zKx1VJsLsfk", "title": "They can fly 200 miles with no fuel. Here's how.", "channel": "Tom Scott", "thumb": "https://img.youtube.com/vi/zKx1VJsLsfk/mqdefault.jpg"}, {"id": "GpaNijzRaJI", "title": "I helped break a 142-year-old bell, and that's okay.", "channel": "Tom Scott", "thumb": "https://img.youtube.com/vi/GpaNijzRaJI/mqdefault.jpg"}, {"id": "F0JDK_71yDg", "title": "People are going to be angry about pylons.", "channel": "Tom Scott", "thumb": "https://img.youtube.com/vi/F0JDK_71yDg/mqdefault.jpg"}, {"id": "Zl_5LT2fzak", "title": "Why the government drops flies on California", "channel": "Tom Scott", "thumb": "https://img.youtube.com/vi/Zl_5LT2fzak/mqdefault.jpg"}, {"id": "hNZy603as5w", "title": "A robot just swapped my electric car's battery", "channel": "Tom Scott", "thumb": "https://img.youtube.com/vi/hNZy603as5w/mqdefault.jpg"}, {"id": "pU9sHwNKc2c", "title": "Why don't subtitles match dubbing?", "channel": "Tom Scott", "thumb": "https://img.youtube.com/vi/pU9sHwNKc2c/mqdefault.jpg"}, {"id": "LDiXNsWQzD0", "title": "Why use many streetlights when one will do?", "channel": "Tom Scott", "thumb": "https://img.youtube.com/vi/LDiXNsWQzD0/mqdefault.jpg"}, {"id": "jplrbxI5GN8", "title": "These tiny ships have a serious purpose", "channel": "Tom Scott", "thumb": "https://img.youtube.com/vi/jplrbxI5GN8/mqdefault.jpg"}, {"id": "CmZdGo6b5yA", "title": "Does the language you speak change how you think?", "channel": "Tom Scott", "thumb": "https://img.youtube.com/vi/CmZdGo6b5yA/mqdefault.jpg"}, {"id": "j3OqAN4ISOw", "title": "Boarding planes could have been very different", "channel": "Tom Scott", "thumb": "https://img.youtube.com/vi/j3OqAN4ISOw/mqdefault.jpg"}, {"id": "XQIu5tZ0vbQ", "title": "0-100 in less than a second. And I'm driving.", "channel": "Tom Scott", "thumb": "https://img.youtube.com/vi/XQIu5tZ0vbQ/mqdefault.jpg"}, {"id": "CkZyZFa5qO0", "title": "there\u2019dn\u2019t\u2019ve", "channel": "Tom Scott", "thumb": "https://img.youtube.com/vi/CkZyZFa5qO0/mqdefault.jpg"}, {"id": "97RPlob5dd8", "title": "How To Draw The Easter Bunny Skateboarding", "channel": "Art for Kids Hub", "thumb": "https://img.youtube.com/vi/97RPlob5dd8/mqdefault.jpg"}, {"id": "LAhnyh9e-Qs", "title": "How To Draw An Easter Kitten", "channel": "Art for Kids Hub", "thumb": "https://img.youtube.com/vi/LAhnyh9e-Qs/mqdefault.jpg"}, {"id": "d8kDHN6rJu4", "title": "How TO Draw A Spring Lamb", "channel": "Art for Kids Hub", "thumb": "https://img.youtube.com/vi/d8kDHN6rJu4/mqdefault.jpg"}, {"id": "QmCOk_hgZQs", "title": "How To Draw An Easter Puppy Golden Retriever", "channel": "Art for Kids Hub", "thumb": "https://img.youtube.com/vi/QmCOk_hgZQs/mqdefault.jpg"}, {"id": "8QNlDuYPEQs", "title": "How To Draw The Easter Bunny In A Basket", "channel": "Art for Kids Hub", "thumb": "https://img.youtube.com/vi/8QNlDuYPEQs/mqdefault.jpg"}, {"id": "MtAMaDgZFOM", "title": "How To Draw Mabel From Disney Pixar Hoppers", "channel": "Art for Kids Hub", "thumb": "https://img.youtube.com/vi/MtAMaDgZFOM/mqdefault.jpg"}, {"id": "dSUtn2z6KMY", "title": "How To Draw A Baby Robin In A Nest", "channel": "Art for Kids Hub", "thumb": "https://img.youtube.com/vi/dSUtn2z6KMY/mqdefault.jpg"}, {"id": "PxQKnrZ-uSc", "title": "How To Draw A Spring Birdhouse", "channel": "Art for Kids Hub", "thumb": "https://img.youtube.com/vi/PxQKnrZ-uSc/mqdefault.jpg"}, {"id": "3MueBnHQ_R8", "title": "How To Draw A Happy Cherry Blossom Tree", "channel": "Art for Kids Hub", "thumb": "https://img.youtube.com/vi/3MueBnHQ_R8/mqdefault.jpg"}, {"id": "F6fzGD2aOmg", "title": "How To Draw A Baby Chick Hatching Out Of An Egg", "channel": "Art for Kids Hub", "thumb": "https://img.youtube.com/vi/F6fzGD2aOmg/mqdefault.jpg"}, {"id": "pE34eK-aGh0", "title": "sketchbook challenge - baby chick! \ud83d\udc24 #artforkidshub \ufffc", "channel": "Art for Kids Hub", "thumb": "https://img.youtube.com/vi/pE34eK-aGh0/mqdefault.jpg"}, {"id": "--rXcww339M", "title": "How To Draw A Cute Ladybug Sitting On A Flower", "channel": "Art for Kids Hub", "thumb": "https://img.youtube.com/vi/--rXcww339M/mqdefault.jpg"}, {"id": "QlPxeBM1ioE", "title": "How To Draw A Baby Deer Fawn For Spring", "channel": "Art for Kids Hub", "thumb": "https://img.youtube.com/vi/QlPxeBM1ioE/mqdefault.jpg"}, {"id": "rwH5wydh_10", "title": "How To Build A Creeper - Minecraft Art", "channel": "Art for Kids Hub", "thumb": "https://img.youtube.com/vi/rwH5wydh_10/mqdefault.jpg"}, {"id": "Fgbf2o33WzU", "title": "How To Draw A Leprechaun Gnome Sitting On A Mushroom", "channel": "Art for Kids Hub", "thumb": "https://img.youtube.com/vi/Fgbf2o33WzU/mqdefault.jpg"}, {"id": "kj1-JRXRJCY", "title": "Kids Yoga LIVE \ud83c\udf1f | Fun Yoga Adventures & Movement for Kids", "channel": "Cosmic Kids Yoga", "thumb": "https://img.youtube.com/vi/kj1-JRXRJCY/mqdefault.jpg"}, {"id": "1stzBGxs9hU", "title": "Who can do the LOUDEST ROAR? | Bebefinn x Cosmic Kids Easter Yoga", "channel": "Cosmic Kids Yoga", "thumb": "https://img.youtube.com/vi/1stzBGxs9hU/mqdefault.jpg"}, {"id": "kEUdl43gU-Q", "title": "Jaime\u2019s Yoga Adventures | WOAH! Too Fast! \ud83d\udc2d Slow Down with Max", "channel": "Cosmic Kids Yoga", "thumb": "https://img.youtube.com/vi/kEUdl43gU-Q/mqdefault.jpg"}, {"id": "ZguLFkqUXP0", "title": "Can you spot the giant egg? | \ud83d\udc23 Fun Easter Yoga for Kids!", "channel": "Cosmic Kids Yoga", "thumb": "https://img.youtube.com/vi/ZguLFkqUXP0/mqdefault.jpg"}, {"id": "uzkte__Tx38", "title": "\ud83d\udd34 The Push Button Song! \ud83d\udd34 | Brain Break for Kids | Hi My Name\u2019s Joe!", "channel": "Cosmic Kids Yoga", "thumb": "https://img.youtube.com/vi/uzkte__Tx38/mqdefault.jpg"}, {"id": "NDV10fjNdCQ", "title": "\ud83d\udd75\ufe0f\u200d\u2640\ufe0fWhat is Jaime's CUNNING PLAN to retrieve the eggs from the Tickley Monkeys?\ud83d\udc35", "channel": "Cosmic Kids Yoga", "thumb": "https://img.youtube.com/vi/NDV10fjNdCQ/mqdefault.jpg"}, {"id": "Dn_uQoCp2_A", "title": "Cosmic Kids x Bebefinn | NEW Easter Adventure! \ud83d\udc23\ud83e\uddd8\u200d\u2640\ufe0f", "channel": "Cosmic Kids Yoga", "thumb": "https://img.youtube.com/vi/Dn_uQoCp2_A/mqdefault.jpg"}, {"id": "ea8f6-jzhv4", "title": "CAN YOU BUNNY HOP? \ud83d\udc30", "channel": "Cosmic Kids Yoga", "thumb": "https://img.youtube.com/vi/ea8f6-jzhv4/mqdefault.jpg"}, {"id": "uFtF6GQzoG8", "title": "What\u2019s Goat\u2019s new invention?! \ud83e\udd16\u2699\ufe0f", "channel": "Cosmic Kids Yoga", "thumb": "https://img.youtube.com/vi/uFtF6GQzoG8/mqdefault.jpg"}, {"id": "az51FjAf4ZU", "title": "Do YOU know what today is? \ud83d\udc49\ud83d\udc0c", "channel": "Cosmic Kids Yoga", "thumb": "https://img.youtube.com/vi/az51FjAf4ZU/mqdefault.jpg"}, {"id": "HX1JNOA2m-A", "title": "\ud83e\udee3HIDE! The Tickly Monkeys are coming!\ud83d\udc35", "channel": "Cosmic Kids Yoga", "thumb": "https://img.youtube.com/vi/HX1JNOA2m-A/mqdefault.jpg"}, {"id": "JBmKXRqSBqw", "title": "Are you a STRONG TREE today?! \ud83c\udf33\ud83d\udcaa", "channel": "Cosmic Kids Yoga", "thumb": "https://img.youtube.com/vi/JBmKXRqSBqw/mqdefault.jpg"}, {"id": "8w02FGPdWT4", "title": "Easter Yoga for Kids \ud83c\udf38 The Missing Eggs Adventure!", "channel": "Cosmic Kids Yoga", "thumb": "https://img.youtube.com/vi/8w02FGPdWT4/mqdefault.jpg"}, {"id": "czivSCaDRi4", "title": "Jaime sings with the Wunzies! Let\u2019s Get Ready to Glow! \u2728 | Kids Yoga Singalong", "channel": "Cosmic Kids Yoga", "thumb": "https://img.youtube.com/vi/czivSCaDRi4/mqdefault.jpg"}, {"id": "WPcYi1XIT-4", "title": "Clapping Challenge ACCEPTED!\ud83d\udc4f\ud83c\udffb\ud83d\udc4f\ud83c\udffb", "channel": "Cosmic Kids Yoga", "thumb": "https://img.youtube.com/vi/WPcYi1XIT-4/mqdefault.jpg"}, {"id": "CVkpN5sQAG4", "title": "Sesame Street: Elmo's World Alphabet, Birthdays, Colors and More LIVE | Elmo Videos for Kids", "channel": "Sesame Street", "thumb": "https://img.youtube.com/vi/CVkpN5sQAG4/mqdefault.jpg"}, {"id": "0JmNOQSJEq8", "title": "Sing ABC Songs with Elmo & Friends | Sesame Street Live", "channel": "Sesame Street", "thumb": "https://img.youtube.com/vi/0JmNOQSJEq8/mqdefault.jpg"}, {"id": "O-sQdSFPxgU", "title": "Hair Appreciation Game! \u2728 #sesamestreet", "channel": "Sesame Street", "thumb": "https://img.youtube.com/vi/O-sQdSFPxgU/mqdefault.jpg"}, {"id": "8hY2bHTjUi0", "title": "Are We There Yet? \ud83d\ude80\ud83c\udf15 #sesamestreet", "channel": "Sesame Street", "thumb": "https://img.youtube.com/vi/8hY2bHTjUi0/mqdefault.jpg"}, {"id": "hJfd1jsaCQ8", "title": "Respect Each Other's Hair! \ud83d\udc95 #sesamestreet", "channel": "Sesame Street", "thumb": "https://img.youtube.com/vi/hJfd1jsaCQ8/mqdefault.jpg"}, {"id": "bmD3l1Eflco", "title": "Elmo's Fruit Salad and Veggies Songs! \ud83c\udf4e\ud83c\udf4c\ud83e\udd55\ud83e\udd66| 90 Mins | Sesame Street", "channel": "Sesame Street", "thumb": "https://img.youtube.com/vi/bmD3l1Eflco/mqdefault.jpg"}, {"id": "yaAKcy25h4A", "title": "Elevator Dance Party! #sesamestreet", "channel": "Sesame Street", "thumb": "https://img.youtube.com/vi/yaAKcy25h4A/mqdefault.jpg"}, {"id": "0QCwbclwsKw", "title": "Baby Cookie Monster on the Run! #sesamestreet", "channel": "Sesame Street", "thumb": "https://img.youtube.com/vi/0QCwbclwsKw/mqdefault.jpg"}, {"id": "W6E-cSECj7Y", "title": "Celebrating YOU! \u263a\ufe0f Positive Affirmations with Elmo & Friends | Sesame Street | 50 Mins", "channel": "Sesame Street", "thumb": "https://img.youtube.com/vi/W6E-cSECj7Y/mqdefault.jpg"}, {"id": "85e5tjboLeM", "title": "Let's Explore Nature! \ud83c\udf3a\ud83c\udf43 | FOUR Sesame Street Full Episodes | 90 Minutes", "channel": "Sesame Street", "thumb": "https://img.youtube.com/vi/85e5tjboLeM/mqdefault.jpg"}, {"id": "RZTFf1FC1Xo", "title": "Abby's Outfit of the Day! #sesamestreet", "channel": "Sesame Street", "thumb": "https://img.youtube.com/vi/RZTFf1FC1Xo/mqdefault.jpg"}, {"id": "uKCxvKh_KTs", "title": "Twinkle Twinkle Little Star \ud83c\udf1f Sing with Elmo! | Sesame Street Songs\ud83c\udfb5", "channel": "Sesame Street", "thumb": "https://img.youtube.com/vi/uKCxvKh_KTs/mqdefault.jpg"}, {"id": "qBv4FYPjnRs", "title": "Playtime with Elmo and Abby!\ud83e\udd29 | Sesame Street | 50 Mins", "channel": "Sesame Street", "thumb": "https://img.youtube.com/vi/qBv4FYPjnRs/mqdefault.jpg"}, {"id": "nq5rzG-LnSg", "title": "Peek-a-Boo Elmo! #sesamestreet", "channel": "Sesame Street", "thumb": "https://img.youtube.com/vi/nq5rzG-LnSg/mqdefault.jpg"}, {"id": "j_z3NxsQutA", "title": "Super Grover Takes a Super Rest! #sesamestreet", "channel": "Sesame Street", "thumb": "https://img.youtube.com/vi/j_z3NxsQutA/mqdefault.jpg"}, {"id": "hI6jai7MwJQ", "title": "\u201cWe\u2019re close to 300km/h!\u201d", "channel": "LEGO", "thumb": "https://img.youtube.com/vi/hI6jai7MwJQ/mqdefault.jpg"}, {"id": "LEia1e4zsEw", "title": "Building a LEGO Speed Champions BUGATTI in a BUGATTI CHIRON", "channel": "LEGO", "thumb": "https://img.youtube.com/vi/LEia1e4zsEw/mqdefault.jpg"}, {"id": "2s8zaVLQFZk", "title": "How Many Z-Blob Clones Are There?! \ud83e\udd2f | Episode 3 | Dream Chaos Shorts | LEGO DREAMZzz Series", "channel": "LEGO", "thumb": "https://img.youtube.com/vi/2s8zaVLQFZk/mqdefault.jpg"}, {"id": "zbmz-bNPtfc", "title": "\ud83d\udc9c NEW Season 4 Teaser | What's Coming Up? \ud83d\udc40 | LEGO Friends: The Next Chapter", "channel": "LEGO", "thumb": "https://img.youtube.com/vi/zbmz-bNPtfc/mqdefault.jpg"}, {"id": "3lHTxd4iXCY", "title": "P\u0159ivedl t\u011b osud \ud83d\ude4c | 4. \u0159ada, 2. d\u00edl | Cel\u00fd d\u00edl | LEGO NINJAGO: Dra\u010d\u00ed povst\u00e1n\u00ed", "channel": "LEGO", "thumb": "https://img.youtube.com/vi/3lHTxd4iXCY/mqdefault.jpg"}, {"id": "E2Qwon07ol4", "title": "\u3055\u3055\u3084\u304d\u306e\u68ee\u3001\u30b0\u30ea\u30fc\u30f3\u30fb\u30cb\u30f3\u30b8\u30e3\u306e\u4f7f\u547d \ud83d\ude4c | S4 E2 | \u30d5\u30eb | \u30ec\u30b4 \u30cb\u30f3\u30b8\u30e3\u30b4\u30fc\uff1a\u30c9\u30e9\u30b4\u30f3\u30e9\u30a4\u30b8\u30f3\u30b0", "channel": "LEGO", "thumb": "https://img.youtube.com/vi/E2Qwon07ol4/mqdefault.jpg"}, {"id": "E8gVH__Jb5k", "title": "Seni Buraya Kader Getirdi \ud83d\ude4c | 4. Sezon, 2. B\u00f6l\u00fcm | Tam B\u00f6l\u00fcm | LEGO NINJAGO: Ejderhalar\u0131n Y\u00fckseli\u015fi", "channel": "LEGO", "thumb": "https://img.youtube.com/vi/E8gVH__Jb5k/mqdefault.jpg"}, {"id": "GWYOUsGjdKs", "title": "Soarta te-a adus aici \ud83d\ude4c | S4, E2 | Episod complet | LEGO NINJAGO: Ascensiunea dragonilor", "channel": "LEGO", "thumb": "https://img.youtube.com/vi/GWYOUsGjdKs/mqdefault.jpg"}, {"id": "Nnk--O0qWsw", "title": "\u547d\u8fd0\u5c06\u4f60\u5e26\u5230\u4e86\u8fd9\u91cc \ud83d\ude4c | \u7b2c 4 \u5b63\uff0c\u7b2c 2 \u96c6 | \u5b8c\u6574\u5267\u96c6 | \u4e50\u9ad8\u5e7b\u5f71\u5fcd\u8005\uff1a\u795e\u9f99\u5d1b\u8d77", "channel": "LEGO", "thumb": "https://img.youtube.com/vi/Nnk--O0qWsw/mqdefault.jpg"}, {"id": "PajOAIPPkK8", "title": "\ub098\ubb34\uac00 \uc790\ub77c\ub294 \ubc29\ud5a5 \ud83d\ude4c | \uc2dc\uc98c 4, \uc5d0\ud53c\uc18c\ub4dc 2 | \ud480\uc601\uc0c1 | \ub808\uace0 \ub2cc\uc790\uace0: \ub4dc\ub798\uace4 \ub77c\uc774\uc9d5", "channel": "LEGO", "thumb": "https://img.youtube.com/vi/PajOAIPPkK8/mqdefault.jpg"}, {"id": "Rx8keZ7OuME", "title": "El destino te trajo aqu\u00ed \ud83d\ude4c | T4, E2 | Completo | LEGO NINJAGO: El Ascenso de los Dragones", "channel": "LEGO", "thumb": "https://img.youtube.com/vi/Rx8keZ7OuME/mqdefault.jpg"}, {"id": "X76i7vBRJyM", "title": "Le destin vous a amen\u00e9 ici \ud83d\ude4c | S4 \u00c92 | Complet | LEGO NINJAGO\u00a0: Le soul\u00e8vement des dragons", "channel": "LEGO", "thumb": "https://img.youtube.com/vi/X76i7vBRJyM/mqdefault.jpg"}, {"id": "ZA-25MUlFOU", "title": "\u0627\u0644\u0642\u062f\u0631 \u0633\u0627\u0642\u0643 \u0625\u0644\u0649 \u0647\u0646\u0627 \ud83d\ude4c | \u0627\u0644\u0645\u0648\u0633\u0645 4\u060c \u0627\u0644\u062d\u0644\u0642\u0629 2 | \u0627\u0644\u062d\u0644\u0642\u0629 \u0627\u0644\u0643\u0627\u0645\u0644\u0629 | LEGO NINJAGO Dragons Rising", "channel": "LEGO", "thumb": "https://img.youtube.com/vi/ZA-25MUlFOU/mqdefault.jpg"}, {"id": "_1JDS6Zui8k", "title": "Az alma a f\u00e1j\u00e1t\u00f3l \ud83d\ude4c | 4. \u00e9vad 2. r\u00e9sz | Teljes epiz\u00f3d | LEGO NINJAGO: S\u00e1rk\u00e1nyok birodalma", "channel": "LEGO", "thumb": "https://img.youtube.com/vi/_1JDS6Zui8k/mqdefault.jpg"}, {"id": "kONDmNVkQzY", "title": "La rivelazione del bosco \ud83d\ude4c | Stagione 4, Ep. 2 | Completo | LEGO NINJAGO: La rivolta dei draghi", "channel": "LEGO", "thumb": "https://img.youtube.com/vi/kONDmNVkQzY/mqdefault.jpg"}, {"id": "rfCCigEO-Ao", "title": "How to Spot Constellations like Orion and Leo \u2b50\ufe0f | The Wonder List | Earth Month \ud83c\udf0e | @natgeokids", "channel": "Nat Geo Kids", "thumb": "https://img.youtube.com/vi/rfCCigEO-Ao/mqdefault.jpg"}, {"id": "yqG1D_JJpjg", "title": "Become a Rock Detective! \ud83d\udd0d \ud83e\udea8 | The Wonder List | Earth Month \ud83c\udf0e | @natgeokids", "channel": "Nat Geo Kids", "thumb": "https://img.youtube.com/vi/yqG1D_JJpjg/mqdefault.jpg"}, {"id": "Ct5zXr5IPFg", "title": "Best Bunny Competition \ud83d\udc30\ud83c\udfc6 | World's Weirdest Pets Compilation | @natgeokids", "channel": "Nat Geo Kids", "thumb": "https://img.youtube.com/vi/Ct5zXr5IPFg/mqdefault.jpg"}, {"id": "-t3rtAJtM-o", "title": "Secrets of the Penguins Full Episode \ud83d\udc27\ud83e\udd2b | Heart of the Emperors | 40 Minutes | @natgeokids", "channel": "Nat Geo Kids", "thumb": "https://img.youtube.com/vi/-t3rtAJtM-o/mqdefault.jpg"}, {"id": "sfuA_Lk-V7E", "title": "Behind the Scenes with Bees! \ud83d\udc1d | Weirdest, Bestest, Truest | @natgeokids", "channel": "Nat Geo Kids", "thumb": "https://img.youtube.com/vi/sfuA_Lk-V7E/mqdefault.jpg"}, {"id": "Bu8ADc1EKx0", "title": "Every 5-Minute Stories Book Read-Along\ud83d\udcda | 40 Minutes | Compilation \ud83e\udd88\ud83d\udc27\ud83d\udc12| @natgeokids\u200b", "channel": "Nat Geo Kids", "thumb": "https://img.youtube.com/vi/Bu8ADc1EKx0/mqdefault.jpg"}, {"id": "SG_ANS6jM8Y", "title": "How to Spot Stars and Constellations in the Sky \u2b50\ufe0f | The Wonder List | Earth Month \ud83c\udf0e | @natgeokids", "channel": "Nat Geo Kids", "thumb": "https://img.youtube.com/vi/SG_ANS6jM8Y/mqdefault.jpg"}, {"id": "k-zvNm2kyxY", "title": "Quick Quiz! How do froglets get their nutrients? \ud83d\udc38 | 5 Minute Stories | @natgeokids\u200b", "channel": "Nat Geo Kids", "thumb": "https://img.youtube.com/vi/k-zvNm2kyxY/mqdefault.jpg"}, {"id": "G6gFPwl_lAc", "title": "5 Minute Stories Book Read-Along \ud83d\udcda | From Tiny Tadpoles to Fabulous Frogs \ud83d\udc38 | @natgeokids", "channel": "Nat Geo Kids", "thumb": "https://img.youtube.com/vi/G6gFPwl_lAc/mqdefault.jpg"}, {"id": "cwzh-fAhL2k", "title": "Quick Quiz! What activity do jaguars like other cats do not?\ud83d\ude3c\ud83d\ude3b | 5 Minute Stories | @natgeokids", "channel": "Nat Geo Kids", "thumb": "https://img.youtube.com/vi/cwzh-fAhL2k/mqdefault.jpg"}, {"id": "metiK21AMn0", "title": "Busy Bees \ud83d\udc1d\ud83c\udf6f | Weird But True Full Episode | @natgeokids", "channel": "Nat Geo Kids", "thumb": "https://img.youtube.com/vi/metiK21AMn0/mqdefault.jpg"}, {"id": "PApZ2oT5SuA", "title": "\ud83d\udd34 LIVE! 24 Hours of Celebrating Earth Month! \ud83c\udf0e \ud83d\udc3b | @natgeokids", "channel": "Nat Geo Kids", "thumb": "https://img.youtube.com/vi/PApZ2oT5SuA/mqdefault.jpg"}, {"id": "dt956XK94FI", "title": "3 Types of Trees & Their Cool Secrets \ud83c\udf34| The Wonder List | Earth Month \ud83c\udf0e | @natgeokids", "channel": "Nat Geo Kids", "thumb": "https://img.youtube.com/vi/dt956XK94FI/mqdefault.jpg"}, {"id": "00F7pKYGtro", "title": "How to Spot Stars and Constellations in the Sky \u2b50\ufe0f| The Wonder List | Earth Month \ud83c\udf0e| @natgeokids", "channel": "Nat Geo Kids", "thumb": "https://img.youtube.com/vi/00F7pKYGtro/mqdefault.jpg"}, {"id": "LlsOaqnqPIE", "title": "30 seconds of baby bighorn sheep \ud83d\udc11 | @natgeokids", "channel": "Nat Geo Kids", "thumb": "https://img.youtube.com/vi/LlsOaqnqPIE/mqdefault.jpg"}, {"id": "_qcFt0kciF4", "title": "\ud83d\udd34 LIVE | Wild Kratts FULL EPISODES MARATHON \ud83e\udd92\ud83d\udc28", "channel": "Wild Kratts - Scholastic", "thumb": "https://img.youtube.com/vi/_qcFt0kciF4/mqdefault.jpg"}, {"id": "oZjJxlY6G4U", "title": "Battle of the Big Horn Sheep | Creature Battles | Wild Kratts", "channel": "Wild Kratts - Scholastic", "thumb": "https://img.youtube.com/vi/oZjJxlY6G4U/mqdefault.jpg"}, {"id": "oK2eUW7z6Lc", "title": "Tiger Mode Activated | Creature Transformation | Wild Kratts", "channel": "Wild Kratts - Scholastic", "thumb": "https://img.youtube.com/vi/oK2eUW7z6Lc/mqdefault.jpg"}, {"id": "OX8srHXgQDw", "title": "A Jack Rabbit's Wild Hop | Creature Abilities | Wild Kratts", "channel": "Wild Kratts - Scholastic", "thumb": "https://img.youtube.com/vi/OX8srHXgQDw/mqdefault.jpg"}, {"id": "bilYblVD-3M", "title": "\ud83d\udd34 LIVE | Wild Kratts FULL EPISODES MARATHON \ud83e\udd92\ud83d\udc28", "channel": "Wild Kratts - Scholastic", "thumb": "https://img.youtube.com/vi/bilYblVD-3M/mqdefault.jpg"}, {"id": "ZvmhGQi5qQw", "title": "Creature Showdown: Turtle vs Crocodile | Creature Battle | Wild Kratts", "channel": "Wild Kratts - Scholastic", "thumb": "https://img.youtube.com/vi/ZvmhGQi5qQw/mqdefault.jpg"}, {"id": "JaXnAbcDPhw", "title": "Trapped Whale Rescue | Creature Rescue | Wild Kratts", "channel": "Wild Kratts - Scholastic", "thumb": "https://img.youtube.com/vi/JaXnAbcDPhw/mqdefault.jpg"}, {"id": "wV5vN1mZgfM", "title": "Ravens Mimicking Sounds | Creature Facts | Wild Kratts", "channel": "Wild Kratts - Scholastic", "thumb": "https://img.youtube.com/vi/wV5vN1mZgfM/mqdefault.jpg"}, {"id": "vfnG2pYDftE", "title": "Battle of the Pony Stallion | Creature Battles | Wild Kratts", "channel": "Wild Kratts - Scholastic", "thumb": "https://img.youtube.com/vi/vfnG2pYDftE/mqdefault.jpg"}, {"id": "LifiynyBy-o", "title": "\ud83d\udd34 LIVE | Wild Kratts FULL EPISODES MARATHON \ud83e\udd92\ud83d\udc28", "channel": "Wild Kratts - Scholastic", "thumb": "https://img.youtube.com/vi/LifiynyBy-o/mqdefault.jpg"}, {"id": "Ii3EczyoFk4", "title": "Transforming Into a Parrot | Creature Transformations | Wild Kratts", "channel": "Wild Kratts - Scholastic", "thumb": "https://img.youtube.com/vi/Ii3EczyoFk4/mqdefault.jpg"}, {"id": "inf3ukPHds8", "title": "The Best Creature Transformations | Creature Transformation | Wild Kratts", "channel": "Wild Kratts - Scholastic", "thumb": "https://img.youtube.com/vi/inf3ukPHds8/mqdefault.jpg"}, {"id": "Y_Y3O2KWayA", "title": "Activate Eagle Owl Powers | Creature Abilities | Wild Kratts", "channel": "Wild Kratts - Scholastic", "thumb": "https://img.youtube.com/vi/Y_Y3O2KWayA/mqdefault.jpg"}, {"id": "mR-PwKQgpK4", "title": "Wild Kratts to the Rescue | FULL EPISODES MARATHON | 5+ Hour Compilation \ud83e\udd92\ud83d\udc28", "channel": "Wild Kratts - Scholastic", "thumb": "https://img.youtube.com/vi/mR-PwKQgpK4/mqdefault.jpg"}, {"id": "r2jMB6n0BC0", "title": "The Best Square Numbers! | Learn to Count for Kids | Number Cartoon | Numberblocks", "channel": "Numberblocks", "thumb": "https://img.youtube.com/vi/r2jMB6n0BC0/mqdefault.jpg"}, {"id": "_Bt2s-ugCXQ", "title": "Nine | Numberblocks COURSE - Level 2, Orange (S2 E4)", "channel": "Numberblocks", "thumb": "https://img.youtube.com/vi/_Bt2s-ugCXQ/mqdefault.jpg"}, {"id": "ICxYnLUzcxE", "title": "Eight | Numberblocks COURSE - Level 2, Orange (S2 E3)", "channel": "Numberblocks", "thumb": "https://img.youtube.com/vi/ICxYnLUzcxE/mqdefault.jpg"}, {"id": "xLyHCCxCW6I", "title": "How Many Easter Animals Can You Count? | Learn to Count for Kids | Number Cartoon | Numberblocks", "channel": "Numberblocks", "thumb": "https://img.youtube.com/vi/xLyHCCxCW6I/mqdefault.jpg"}, {"id": "Bu0-ACSBy7g", "title": "Seven | Numberblocks COURSE - Level 2, Orange (S2 E2)", "channel": "Numberblocks", "thumb": "https://img.youtube.com/vi/Bu0-ACSBy7g/mqdefault.jpg"}, {"id": "qdhWvna6CvU", "title": "Happy Easter - Awesome Numberblob Hunt! | Learn to Count for Kids | Number Cartoon | Numberblocks", "channel": "Numberblocks", "thumb": "https://img.youtube.com/vi/qdhWvna6CvU/mqdefault.jpg"}, {"id": "GtW9AJO6vKM", "title": "Learn to Love Math! | Learn to Count | Learn to Count for Kids | Number Cartoon | Numberblocks", "channel": "Numberblocks", "thumb": "https://img.youtube.com/vi/GtW9AJO6vKM/mqdefault.jpg"}, {"id": "-aZRIu0-d9c", "title": "Fabulous First Grade Math | Learn to Count for Kids | Number Cartoon | Numberblocks", "channel": "Numberblocks", "thumb": "https://img.youtube.com/vi/-aZRIu0-d9c/mqdefault.jpg"}, {"id": "ivIkoGjVxJk", "title": "\ud83e\udd5a Numberblocks Easter Special! \ud83d\udc30 | Happy Easter! LIVE | Counting for Kids | Numberblocks", "channel": "Numberblocks", "thumb": "https://img.youtube.com/vi/ivIkoGjVxJk/mqdefault.jpg"}, {"id": "oH6M1SB0v_k", "title": "Magical Maths with Numberblock 100! | Learn to Count for Kids | Number Cartoon | Numberblocks", "channel": "Numberblocks", "thumb": "https://img.youtube.com/vi/oH6M1SB0v_k/mqdefault.jpg"}, {"id": "D83i-K9rx0w", "title": "How To Count | Numberblocks - Level 1, Red (S1 E10)", "channel": "Numberblocks", "thumb": "https://img.youtube.com/vi/D83i-K9rx0w/mqdefault.jpg"}, {"id": "8VfwAS11QKs", "title": "Off We Go! | Numberblocks COURSE - Level 1, Red (S1 E9)", "channel": "Numberblocks", "thumb": "https://img.youtube.com/vi/8VfwAS11QKs/mqdefault.jpg"}, {"id": "wP9tat9UKQ8", "title": "Three Little Pigs | Numberblocks COURSE - Level 1, Red (S1 E8)", "channel": "Numberblocks", "thumb": "https://img.youtube.com/vi/wP9tat9UKQ8/mqdefault.jpg"}, {"id": "wAq4Y-tMkUs", "title": "One Hundred! | Numberblocks COURSE - Level 5, Blue (S4 E26)", "channel": "Numberblocks", "thumb": "https://img.youtube.com/vi/wAq4Y-tMkUs/mqdefault.jpg"}, {"id": "BPVlg-oaklo", "title": "Twenty One and One | Numberblocks COURSE - Level 4, Green (S4 E21)", "channel": "Numberblocks", "thumb": "https://img.youtube.com/vi/BPVlg-oaklo/mqdefault.jpg"}, {"id": "PkWU-lMdnJg", "title": "How to compare and contrast (Little Red Riding Hood): Crash Course Kids Literature #6", "channel": "Crash Course Kids", "thumb": "https://img.youtube.com/vi/PkWU-lMdnJg/mqdefault.jpg"}, {"id": "klu7TNy-7qw", "title": "Poetry explained (Inside Out & Back Again by Thanhh\u00e0 L\u1ea1i): Crash Course Kids Literature #5", "channel": "Crash Course Kids", "thumb": "https://img.youtube.com/vi/klu7TNy-7qw/mqdefault.jpg"}, {"id": "ML2oX207Mwc", "title": "Understanding nonfiction: Crash Course Kids Literature #4", "channel": "Crash Course Kids", "thumb": "https://img.youtube.com/vi/ML2oX207Mwc/mqdefault.jpg"}, {"id": "QVw521JjRjA", "title": "How to find themes (A Wrinkle in Time): Crash Course Kids Literature #3", "channel": "Crash Course Kids", "thumb": "https://img.youtube.com/vi/QVw521JjRjA/mqdefault.jpg"}, {"id": "WrUX6j9MwUY", "title": "Character Traits Explained (King and the Dragonflies): Crash Course Kids Literature #2", "channel": "Crash Course Kids", "thumb": "https://img.youtube.com/vi/WrUX6j9MwUY/mqdefault.jpg"}, {"id": "XjR2B3YJH9U", "title": "What is an inference? (Charlotte\u2019s Web): Crash Course Kids Literature #1", "channel": "Crash Course Kids", "thumb": "https://img.youtube.com/vi/XjR2B3YJH9U/mqdefault.jpg"}, {"id": "ui86G8Q5GhQ", "title": "Crash Course Kids Literature Preview", "channel": "Crash Course Kids", "thumb": "https://img.youtube.com/vi/ui86G8Q5GhQ/mqdefault.jpg"}, {"id": "JcxTM7knO80", "title": "Welcome to Crash Course Kids!", "channel": "Crash Course Kids", "thumb": "https://img.youtube.com/vi/JcxTM7knO80/mqdefault.jpg"}, {"id": "EwY6p-r_hyU", "title": "Gravity Compilation: Crash Course Kids", "channel": "Crash Course Kids", "thumb": "https://img.youtube.com/vi/EwY6p-r_hyU/mqdefault.jpg"}, {"id": "wyRy8kowyM8", "title": "Matter Compilation: Crash Course Kids", "channel": "Crash Course Kids", "thumb": "https://img.youtube.com/vi/wyRy8kowyM8/mqdefault.jpg"}, {"id": "CZhE2p46vJk", "title": "Food Chains Compilation: Crash Course Kids", "channel": "Crash Course Kids", "thumb": "https://img.youtube.com/vi/CZhE2p46vJk/mqdefault.jpg"}, {"id": "Td_A9H69eE8", "title": "Space Compilation: Crash Course Kids", "channel": "Crash Course Kids", "thumb": "https://img.youtube.com/vi/Td_A9H69eE8/mqdefault.jpg"}, {"id": "qDcMq1SjR_I", "title": "Engineering Compilation: Crash Course Kids", "channel": "Crash Course Kids", "thumb": "https://img.youtube.com/vi/qDcMq1SjR_I/mqdefault.jpg"}, {"id": "s__sgOHWNIA", "title": "The End Is Only The Beginning: Crash Course Kids #48.2", "channel": "Crash Course Kids", "thumb": "https://img.youtube.com/vi/s__sgOHWNIA/mqdefault.jpg"}, {"id": "gnnUid8Hof0", "title": "Let's Build a City: Crash Course Kids #48.1", "channel": "Crash Course Kids", "thumb": "https://img.youtube.com/vi/gnnUid8Hof0/mqdefault.jpg"}, {"id": "ipfd3t0-6K4", "title": "Animal Lessons for Kids | Learn About Land and Sea Animals", "channel": "Homeschool Pop", "thumb": "https://img.youtube.com/vi/ipfd3t0-6K4/mqdefault.jpg"}, {"id": "aDYHBiXxmSA", "title": "Do Butterflies Really Taste with Their Feet?", "channel": "Homeschool Pop", "thumb": "https://img.youtube.com/vi/aDYHBiXxmSA/mqdefault.jpg"}, {"id": "KCsXv3cTr-s", "title": "Spanish Lessons for Kids | Body Parts, Colors, Animals, Food & More", "channel": "Homeschool Pop", "thumb": "https://img.youtube.com/vi/KCsXv3cTr-s/mqdefault.jpg"}, {"id": "INEv8XMaay0", "title": "Today Is the First Day of Spring!", "channel": "Homeschool Pop", "thumb": "https://img.youtube.com/vi/INEv8XMaay0/mqdefault.jpg"}, {"id": "a43KsAGZOvc", "title": "Language Arts Lessons for Kids | Grammar, Figurative Language & More", "channel": "Homeschool Pop", "thumb": "https://img.youtube.com/vi/a43KsAGZOvc/mqdefault.jpg"}, {"id": "KHlxfqSG4GQ", "title": "I Learned to Play This as a Kid!", "channel": "Homeschool Pop", "thumb": "https://img.youtube.com/vi/KHlxfqSG4GQ/mqdefault.jpg"}, {"id": "LEf68eCdtto", "title": "Body Parts in Spanish for Kids | Spanish Vocabulary Lesson", "channel": "Homeschool Pop", "thumb": "https://img.youtube.com/vi/LEf68eCdtto/mqdefault.jpg"}, {"id": "WUMcBkFTkXk", "title": "Social Studies Lessons for Kids | Landmarks and Economics", "channel": "Homeschool Pop", "thumb": "https://img.youtube.com/vi/WUMcBkFTkXk/mqdefault.jpg"}, {"id": "FJIQbJDM_Lw", "title": "A Flower That Blooms in the Cold?!", "channel": "Homeschool Pop", "thumb": "https://img.youtube.com/vi/FJIQbJDM_Lw/mqdefault.jpg"}, {"id": "snBlsf1Yv_A", "title": "Math Marathon for Kids | Big Elementary Math Review", "channel": "Homeschool Pop", "thumb": "https://img.youtube.com/vi/snBlsf1Yv_A/mqdefault.jpg"}, {"id": "v7BdT1Ll32E", "title": "Big News: I\u2019m Going Live Every Week!", "channel": "Homeschool Pop", "thumb": "https://img.youtube.com/vi/v7BdT1Ll32E/mqdefault.jpg"}, {"id": "e1CCwuiB57Q", "title": "Famous Americans for Kids | Biography Compilation", "channel": "Homeschool Pop", "thumb": "https://img.youtube.com/vi/e1CCwuiB57Q/mqdefault.jpg"}, {"id": "uRke2EtIwBE", "title": "Can Owls Really Fly Almost Silently?", "channel": "Homeschool Pop", "thumb": "https://img.youtube.com/vi/uRke2EtIwBE/mqdefault.jpg"}, {"id": "sZ1DL6a1p8A", "title": "Science Lessons for Kids | Explore the World & Beyond", "channel": "Homeschool Pop", "thumb": "https://img.youtube.com/vi/sZ1DL6a1p8A/mqdefault.jpg"}, {"id": "UZAiUJKSqfU", "title": "Learn the U.S. States: The Mid-Atlantic Region", "channel": "Homeschool Pop", "thumb": "https://img.youtube.com/vi/UZAiUJKSqfU/mqdefault.jpg"}, {"id": "vNE1zzCvR9Q", "title": "We found Tom's doppelganger", "channel": "The Yogscast", "thumb": "https://img.youtube.com/vi/vNE1zzCvR9Q/mqdefault.jpg"}, {"id": "Ou1ERBAR_vM", "title": "This NEW ROLE is SoOoO Random!! | Gmod TTT", "channel": "The Yogscast", "thumb": "https://img.youtube.com/vi/Ou1ERBAR_vM/mqdefault.jpg"}, {"id": "6t1ZOgxxn5U", "title": "New Chef Role COOKS in Gmod TTT!", "channel": "The Yogscast", "thumb": "https://img.youtube.com/vi/6t1ZOgxxn5U/mqdefault.jpg"}, {"id": "85EKquwCppE", "title": "Let's Make a Deal - Blood on the Clocktower in Minecraft LIVE", "channel": "The Yogscast", "thumb": "https://img.youtube.com/vi/85EKquwCppE/mqdefault.jpg"}, {"id": "Tguvi-nBelE", "title": "The Golden Carrot Gang | Murder on Minecraft Express", "channel": "The Yogscast", "thumb": "https://img.youtube.com/vi/Tguvi-nBelE/mqdefault.jpg"}, {"id": "tm9Dci273Vg", "title": "Famous last words! #ad", "channel": "The Yogscast", "thumb": "https://img.youtube.com/vi/tm9Dci273Vg/mqdefault.jpg"}, {"id": "qzTqPTcl6qs", "title": "The Ultimate Yogscast Minecrafters! | 100 Ways to Die GRAND FINAL", "channel": "The Yogscast", "thumb": "https://img.youtube.com/vi/qzTqPTcl6qs/mqdefault.jpg"}, {"id": "mC78Adz93e0", "title": "Glooking                                               #gloving #cooking", "channel": "You Suck At Cooking", "thumb": "https://img.youtube.com/vi/mC78Adz93e0/mqdefault.jpg"}, {"id": "BA81fFoHVI8", "title": "Onion DNA", "channel": "You Suck At Cooking", "thumb": "https://img.youtube.com/vi/BA81fFoHVI8/mqdefault.jpg"}, {"id": "-J7kZYaEUYA", "title": "Grilled Cheese", "channel": "You Suck At Cooking", "thumb": "https://img.youtube.com/vi/-J7kZYaEUYA/mqdefault.jpg"}, {"id": "3lRRU7b50_k", "title": "Most toxic fruits                                   #toxic #fruit", "channel": "You Suck At Cooking", "thumb": "https://img.youtube.com/vi/3lRRU7b50_k/mqdefault.jpg"}, {"id": "C3KscDoPZnM", "title": "Never wash your knife again               #chop #knife #parchment", "channel": "You Suck At Cooking", "thumb": "https://img.youtube.com/vi/C3KscDoPZnM/mqdefault.jpg"}, {"id": "eYRSbHVyhbY", "title": "24 days to love a food you hate", "channel": "You Suck At Cooking", "thumb": "https://img.youtube.com/vi/eYRSbHVyhbY/mqdefault.jpg"}, {"id": "EW4jBtph6BU", "title": "Getting Jacked             #jackolantern #halloween", "channel": "You Suck At Cooking", "thumb": "https://img.youtube.com/vi/EW4jBtph6BU/mqdefault.jpg"}, {"id": "BC-JwuihUmU", "title": "Jack-O-Lantering Everything - You Suck at Cooking (episode 179)", "channel": "You Suck At Cooking", "thumb": "https://img.youtube.com/vi/BC-JwuihUmU/mqdefault.jpg"}, {"id": "c5bfZ4LB5Zg", "title": "Easy 1 Minute Meal", "channel": "You Suck At Cooking", "thumb": "https://img.youtube.com/vi/c5bfZ4LB5Zg/mqdefault.jpg"}, {"id": "m0p57olODjA", "title": "Crispy Air Fried Potatoes with Awesome Sauce - You Suck at Cooking (episode 178)", "channel": "You Suck At Cooking", "thumb": "https://img.youtube.com/vi/m0p57olODjA/mqdefault.jpg"}, {"id": "EGSL_Mp6RJQ", "title": "Cooking with Sand                           #egg #hardboiledeggs", "channel": "You Suck At Cooking", "thumb": "https://img.youtube.com/vi/EGSL_Mp6RJQ/mqdefault.jpg"}, {"id": "M26uz0BayDw", "title": "Hobby Cooking", "channel": "You Suck At Cooking", "thumb": "https://img.youtube.com/vi/M26uz0BayDw/mqdefault.jpg"}, {"id": "Ry6i6EyvYeE", "title": "Is a $16 tomato worth it?", "channel": "You Suck At Cooking", "thumb": "https://img.youtube.com/vi/Ry6i6EyvYeE/mqdefault.jpg"}, {"id": "u9-v8cxysHM", "title": "Do not put carrots in the fridge #carrot", "channel": "You Suck At Cooking", "thumb": "https://img.youtube.com/vi/u9-v8cxysHM/mqdefault.jpg"}, {"id": "3kjEOOdAlNU", "title": "Snacks                                                      #chips #nuts #doechii", "channel": "You Suck At Cooking", "thumb": "https://img.youtube.com/vi/3kjEOOdAlNU/mqdefault.jpg"}, {"id": "DUAg0sUx9xY", "title": "Japanese Coffee Jelly \u2615\ufe0f", "channel": "Tasty", "thumb": "https://img.youtube.com/vi/DUAg0sUx9xY/mqdefault.jpg"}, {"id": "9FskF92bfdw", "title": "Easy Crepes Hack \ud83e\udd5e\u2728", "channel": "Tasty", "thumb": "https://img.youtube.com/vi/9FskF92bfdw/mqdefault.jpg"}, {"id": "OJPPaDpoQ20", "title": "I Ate Like The XO Kitty Cast For 24 Hours In Korea", "channel": "Tasty", "thumb": "https://img.youtube.com/vi/OJPPaDpoQ20/mqdefault.jpg"}, {"id": "Sa8v5tTn8HY", "title": "I Ate Like The XO Kitty Cast For 24 Hours In Korea", "channel": "Tasty", "thumb": "https://img.youtube.com/vi/Sa8v5tTn8HY/mqdefault.jpg"}, {"id": "HTqMXyvv_rM", "title": "Mango Beautiful Dessert \ud83e\udd6d", "channel": "Tasty", "thumb": "https://img.youtube.com/vi/HTqMXyvv_rM/mqdefault.jpg"}, {"id": "i5faKmyosWc", "title": "Ginger Milk Curd \ud83e\udeda\ud83e\udd5b", "channel": "Tasty", "thumb": "https://img.youtube.com/vi/i5faKmyosWc/mqdefault.jpg"}, {"id": "MNI4ItaLQG4", "title": "Eggs 100 Ways Ep 3 Ostrich Deviled Egg", "channel": "Tasty", "thumb": "https://img.youtube.com/vi/MNI4ItaLQG4/mqdefault.jpg"}, {"id": "F4BkRXcIsBw", "title": "Mini Spam Musubi \ud83c\udf59", "channel": "Tasty", "thumb": "https://img.youtube.com/vi/F4BkRXcIsBw/mqdefault.jpg"}, {"id": "vKr_XzfKzR4", "title": "Poblano Peppers 101", "channel": "Tasty", "thumb": "https://img.youtube.com/vi/vKr_XzfKzR4/mqdefault.jpg"}, {"id": "hIbYhNGKWvQ", "title": "We Recreated The Viral Orange Chicken Fries", "channel": "Tasty", "thumb": "https://img.youtube.com/vi/hIbYhNGKWvQ/mqdefault.jpg"}, {"id": "0pcqdBPnVGI", "title": "How To Make The Viral Orange Chicken Fries", "channel": "Tasty", "thumb": "https://img.youtube.com/vi/0pcqdBPnVGI/mqdefault.jpg"}, {"id": "blxjEjq6Qvc", "title": "POV: Sang Heon Lee from XO Kitty makes you ramen \ud83c\udf5c", "channel": "Tasty", "thumb": "https://img.youtube.com/vi/blxjEjq6Qvc/mqdefault.jpg"}, {"id": "pvbUaQPD1as", "title": "Which XO Kitty Star Cooks the BEST Ramen?", "channel": "Tasty", "thumb": "https://img.youtube.com/vi/pvbUaQPD1as/mqdefault.jpg"}, {"id": "xIBzfprYSFg", "title": "Angel Egg Potato Salad", "channel": "Tasty", "thumb": "https://img.youtube.com/vi/xIBzfprYSFg/mqdefault.jpg"}, {"id": "sAl49h8Iyas", "title": "Vincent D\u2019Onofrio shows Seth a magic trick \ud83e\ude84", "channel": "Late Night with Seth Meyers", "thumb": "https://img.youtube.com/vi/sAl49h8Iyas/mqdefault.jpg"}]}